tests/__init__.py
tests/api_test.py
tests/cli_test.py
tests/conftest.py
tests/exceptions_test.py
tests/utils_test.py
tests/validators_test.py
tests/video_test.py
videoxt/__init__.py
videoxt/api.py
videoxt/cli.py
videoxt/constants.py
videoxt/editors.py
videoxt/exceptions.py
videoxt/extractors.py
videoxt/handlers.py
videoxt/preppers.py
videoxt/py.typed
videoxt/requesters.py
videoxt/result.py
videoxt/utils.py
videoxt/validators.py
videoxt/video.py
videoxt-1.1.6.dist-info/LICENSE
videoxt-1.1.6.dist-info/METADATA
videoxt-1.1.6.dist-info/WHEEL
videoxt-1.1.6.dist-info/entry_points.txt
videoxt-1.1.6.dist-info/top_level.txt
videoxt-1.1.6.dist-info/RECORD
