Metadata-Version: 2.1
Name: videoxt
Version: 1.1.6
Summary: Extract audio, individual frames, short clips and GIFs from videos.
Home-page: https://github.com/gurrutia/videoxt
Author: Gerardo Urrutia
Author-email: durru7@gmail.com
License: MIT
Keywords: video,frame,image,gif,audio,extract,convert,ffmpeg,moviepy,opencv
Classifier: License :: OSI Approved :: MIT License
Classifier: Programming Language :: Python :: 3
Classifier: Programming Language :: Python :: 3 :: Only
Classifier: Topic :: Multimedia :: Graphics
Classifier: Topic :: Multimedia :: Sound/Audio
Classifier: Topic :: Multimedia :: Video
Classifier: Topic :: Utilities
Requires-Python: >=3.10
License-File: LICENSE
Requires-Dist: moviepy >=1.0.3
Requires-Dist: numpy >=1.26.1
Requires-Dist: opencv-python >=4.8.1.78
Requires-Dist: rich >=13.6.0
Provides-Extra: testing
Requires-Dist: coverage >=7.3.2 ; extra == 'testing'
Requires-Dist: pytest >=7.4.3 ; extra == 'testing'
